ocrd_kraken/__init__.py
ocrd_kraken/binarize.py
ocrd_kraken/cli.py
ocrd_kraken/config.py
ocrd_kraken/ocrd-tool.json
ocrd_kraken/recognize.py
ocrd_kraken/segment.py
ocrd_kraken/cli/__init__.py
ocrd_kraken/cli/binarize.py
ocrd_kraken/cli/recognize.py
ocrd_kraken/cli/segment.py
ocrd_kraken-0.4.1.dist-info/LICENSE
ocrd_kraken-0.4.1.dist-info/METADATA
ocrd_kraken-0.4.1.dist-info/WHEEL
ocrd_kraken-0.4.1.dist-info/entry_points.txt
ocrd_kraken-0.4.1.dist-info/top_level.txt
ocrd_kraken-0.4.1.dist-info/RECORD
