Metadata-Version: 2.1
Name: ocrd_kraken
Version: 0.4.1
Summary: Kraken bindings
Home-page: https://github.com/OCR-D/ocrd_kraken
Author: Konstantin Baierer, Robert Sachunsky
Author-email: unixprog@gmail.com, sachunsky@informatik.uni-leipzig.de
License: Apache License 2.0
License-File: LICENSE
Requires-Dist: ocrd >=2.65
Requires-Dist: kraken >=5.0
Requires-Dist: scipy
Requires-Dist: shapely
